trade_strategy/__about__.py
trade_strategy/__init__.py
trade_strategy/portfolio_construction/__init__.py
trade_strategy/portfolio_construction/return_allocations/__init__.py
trade_strategy/portfolio_construction/return_allocations/allocations.py
trade_strategy/portfolio_construction/return_allocations/efficient_frontier.py
trade_strategy-0.1.2.dist-info/METADATA
trade_strategy-0.1.2.dist-info/WHEEL
trade_strategy-0.1.2.dist-info/licenses/LICENSE
trade_strategy-0.1.2.dist-info/RECORD
