Metadata-Version: 2.4
Name: trade-strategy
Version: 0.1.2
Summary: A Python package for analyzing investment portfolios, including using quantitative methods like the efficient frontier for calculations an optimal asset allocation strategy.
Project-URL: Documentation, https://github.com/zerubabeldinsa/trade-strategy#readme
Project-URL: Repository, https://github.com/zerubabeldinsa/trade_strategy
Project-URL: Issues, https://github.com/zerubabeldinsa/trade-strategy/issues
Project-URL: Source, https://github.com/zerubabeldinsa/trade-strategy
Author-email: zerubabeldinsa <zerubabel.dinsa@outlook.com>
License-Expression: MIT
License-File: LICENSE
Classifier: Development Status :: 4 - Beta
Classifier: Programming Language :: Python
Classifier: Programming Language :: Python :: 3.8
Classifier: Programming Language :: Python :: 3.9
Classifier: Programming Language :: Python :: 3.10
Classifier: Programming Language :: Python :: 3.11
Classifier: Programming Language :: Python :: 3.12
Classifier: Programming Language :: Python :: Implementation :: CPython
Classifier: Programming Language :: Python :: Implementation :: PyPy
Requires-Python: >=3.10
Requires-Dist: numpy
Requires-Dist: pandas
Requires-Dist: yfinance
